{
  "project_info": {
    "project_number": "264972265861",
    "project_id": "aula-1-aprendendofbcloud",
    "storage_bucket": "aula-1-aprendendofbcloud.appspot.com"
  },
  "client": [
    {
      "client_info": {
        "mobilesdk_app_id": "1:264972265861:android:73647df9950800c5debcec",
        "android_client_info": {
          "package_name": "com.example.aprendendo2"
        }
      },
      "oauth_client": [],
      "api_key": [
        {
          "current_key": "AIzaSyCX1_p_Ixii5s-stEU2zPPx4174ca1bUkI"
        }
      ],
      "services": {
        "appinvite_service": {
          "other_platform_oauth_client": []
        }
      }
    }
  ],
  "configuration_version": "1"
}